opencorpora/__init__.py
opencorpora/cli.py
opencorpora/compat.py
opencorpora/reader.py
opencorpora/reader_lxml.py
opencorpora/xml_utils.py
opencorpora_tools-0.6.data/scripts/opencorpora
opencorpora_tools-0.6.dist-info/LICENSE.txt
opencorpora_tools-0.6.dist-info/METADATA
opencorpora_tools-0.6.dist-info/WHEEL
opencorpora_tools-0.6.dist-info/pbr.json
opencorpora_tools-0.6.dist-info/top_level.txt
opencorpora_tools-0.6.dist-info/RECORD
